kpmx-1.11.0.dist-info/licenses/LICENSE
pkgmgr/__init__.py
pkgmgr/__main__.py
pkgmgr/actions/__init__.py
pkgmgr/actions/proxy.py
pkgmgr/actions/branch/__init__.py
pkgmgr/actions/branch/close_branch.py
pkgmgr/actions/branch/drop_branch.py
pkgmgr/actions/branch/open_branch.py
pkgmgr/actions/changelog/__init__.py
pkgmgr/actions/config/__init__.py
pkgmgr/actions/config/add.py
pkgmgr/actions/config/init.py
pkgmgr/actions/config/show.py
pkgmgr/actions/install/__init__.py
pkgmgr/actions/install/capabilities.py
pkgmgr/actions/install/context.py
pkgmgr/actions/install/layers.py
pkgmgr/actions/install/pipeline.py
pkgmgr/actions/install/installers/__init__.py
pkgmgr/actions/install/installers/base.py
pkgmgr/actions/install/installers/makefile.py
pkgmgr/actions/install/installers/python.py
pkgmgr/actions/install/installers/nix/__init__.py
pkgmgr/actions/install/installers/nix/conflicts.py
pkgmgr/actions/install/installers/nix/installer.py
pkgmgr/actions/install/installers/nix/profile_list.py
pkgmgr/actions/install/installers/nix/retry.py
pkgmgr/actions/install/installers/nix/runner.py
pkgmgr/actions/install/installers/nix/textparse.py
pkgmgr/actions/install/installers/nix/types.py
pkgmgr/actions/install/installers/nix/profile/__init__.py
pkgmgr/actions/install/installers/nix/profile/inspector.py
pkgmgr/actions/install/installers/nix/profile/matcher.py
pkgmgr/actions/install/installers/nix/profile/models.py
pkgmgr/actions/install/installers/nix/profile/normalizer.py
pkgmgr/actions/install/installers/nix/profile/parser.py
pkgmgr/actions/install/installers/nix/profile/result.py
pkgmgr/actions/install/installers/os_packages/__init__.py
pkgmgr/actions/install/installers/os_packages/arch_pkgbuild.py
pkgmgr/actions/install/installers/os_packages/debian_control.py
pkgmgr/actions/install/installers/os_packages/rpm_spec.py
pkgmgr/actions/mirror/__init__.py
pkgmgr/actions/mirror/context.py
pkgmgr/actions/mirror/diff_cmd.py
pkgmgr/actions/mirror/git_remote.py
pkgmgr/actions/mirror/io.py
pkgmgr/actions/mirror/list_cmd.py
kpmx-1.11.0.dist-info/METADATA
kpmx-1.11.0.dist-info/WHEEL
kpmx-1.11.0.dist-info/entry_points.txt
kpmx-1.11.0.dist-info/top_level.txt
kpmx-1.11.0.dist-info/RECORD
