Metadata-Version: 2.4
Name: kpmx
Version: 1.11.0
Summary: Kevin's package-manager tool (pkgmgr)
Author-email: Kevin Veen-Birkenbach <info@veen.world>
License: MIT
Project-URL: Homepage, https://s.veen.world/pkgmgr
Project-URL: Source, https://github.com/kevinveenbirkenbach/package-manager
Requires-Python: >=3.9
License-File: LICENSE
Requires-Dist: PyYAML>=6.0
Requires-Dist: tomli; python_version < "3.11"
Requires-Dist: jinja2>=3.1
Provides-Extra: keyring
Requires-Dist: keyring>=24.0.0; extra == "keyring"
Provides-Extra: dev
Requires-Dist: mypy; extra == "dev"
Dynamic: license-file
